{"progress": {"completed": 196, "pending": 30, "in_progress": 0}, "roi": {"hours_saved": 392, "active_agents": 0}, "batch": {"current": 1, "total": 16}, "posture": {"security": "Zero-Trust (PR-Gated)", "resilience": "Stateless Auto-Resume Active"}, "batch_details": [{"batch": 1, "total": 59, "completed": 3, "in_progress": 0, "pending": 56}, {"batch": 2, "total": 50, "completed": 0, "in_progress": 0, "pending": 50}, {"batch": 3, "total": 16, "completed": 0, "in_progress": 0, "pending": 16}, {"batch": 4, "total": 14, "completed": 0, "in_progress": 0, "pending": 14}, {"batch": 5, "total": 12, "completed": 0, "in_progress": 0, "pending": 12}, {"batch": 6, "total": 23, "completed": 0, "in_progress": 0, "pending": 23}, {"batch": 7, "total": 14, "completed": 0, "in_progress": 0, "pending": 14}, {"batch": 8, "total": 17, "completed": 0, "in_progress": 0, "pending": 17}, {"batch": 9, "total": 12, "completed": 0, "in_progress": 0, "pending": 12}, {"batch": 10, "total": 3, "completed": 0, "in_progress": 0, "pending": 3}, {"batch": 11, "total": 1, "completed": 0, "in_progress": 0, "pending": 1}, {"batch": 12, "total": 1, "completed": 0, "in_progress": 0, "pending": 1}, {"batch": 13, "total": 1, "completed": 0, "in_progress": 0, "pending": 1}, {"batch": 14, "total": 1, "completed": 0, "in_progress": 0, "pending": 1}, {"batch": 15, "total": 1, "completed": 0, "in_progress": 0, "pending": 1}, {"batch": 16, "total": 1, "completed": 0, "in_progress": 0, "pending": 1}]}